[
  {
    "value": "Front-End Developer"
  },
  {
    "value": "Back-End Developer"
  },
  {
    "value": "Web Developer"
  },
  {
    "value": "Full-Stack Developer"
  },
  {
    "value": "UI/UX Designer"
  },
  {
    "value": "Business Development"
  },
  {
    "value": "Financial Analyst"
  },
  {
    "value": "Data Scientist"
  },
  {
    "value": "Data Analyst"
  },
  {
    "value": "Tester"
  },
  {
    "value": "Financial Tech"
  },
  {
    "value": "CEO"
  },
  {
    "value": "CTO"
  },
  {
    "value": "Digital Media Associate"
  },
  {
    "value": "Content Strategy"
  },
  {
    "value": "Business Development Intern"
  },
  {
    "value": "Customer Service Intern"
  },
  {
    "value": "Operations Intern"
  },
  {
    "value": "Software Engineer"
  },
  {
    "value": "Brand Ambassador"
  },
  {
    "value": "UX/UI"
  },
  {
    "value": "HR Assistant"
  },
  {
    "value": "Marketing"
  },
  {
    "value": "Social Media"
  } 
]